{"bomFormat":"CycloneDX","specVersion":"1.6","serialNumber":"urn:uuid:028a8eb1-ce46-4425-8552-0f3d2c6d2472","version":1,"metadata":{"timestamp":"2025-01-07T16:16:59Z","tools":{"components":[{"group":"@cyclonedx","name":"cdxgen","version":"11.0.11","purl":"pkg:npm/%40cyclonedx/cdxgen@11.0.11","type":"application","bom-ref":"pkg:npm/@cyclonedx/cdxgen@11.0.11","publisher":"OWASP Foundation","authors":[{"name":"OWASP Foundation"}]}]},"authors":[{"name":"OWASP Foundation"}],"lifecycles":[{"phase":"build"}],"component":{"group":"","name":"app","version":"latest","type":"application","bom-ref":"pkg:pypi/app@latest","purl":"pkg:pypi/app@latest"},"properties":[{"name":"cdx:bom:componentTypes","value":"pypi"}]},"components":[{"group":"","name":"whatever","version":"0.7","purl":"pkg:pypi/whatever@0.7","type":"library","bom-ref":"pkg:pypi/whatever@0.7","properties":[{"name":"SrcFile","value":"/app/test_requirements.txt"},{"name":"SrcFile","value":"/app/setup.py"}],"evidence":{"identity":[{"field":"purl","confidence":0.5,"methods":[{"technique":"instrumentation","confidence":0.5,"value":"/tmp/cdxgen-venv-3oZ5Ee"}],"concludedValue":"/tmp/cdxgen-venv-3oZ5Ee"}]}},{"group":"","name":"pytest","version":"7.4.3","purl":"pkg:pypi/pytest@7.4.3","type":"library","bom-ref":"pkg:pypi/pytest@7.4.3","properties":[{"name":"SrcFile","value":"/app/test_requirements.txt"},{"name":"SrcFile","value":"/app/setup.py"}],"evidence":{"identity":[{"field":"purl","confidence":0.5,"methods":[{"technique":"instrumentation","confidence":0.5,"value":"/tmp/cdxgen-venv-3oZ5Ee"}],"concludedValue":"/tmp/cdxgen-venv-3oZ5Ee"}]}},{"group":"","name":"tomli","version":"2.2.1","purl":"pkg:pypi/tomli@2.2.1","type":"library","bom-ref":"pkg:pypi/tomli@2.2.1","properties":[{"name":"SrcFile","value":"/app/test_requirements.txt"},{"name":"SrcFile","value":"/app/setup.py"}],"evidence":{"identity":[{"field":"purl","confidence":0.8,"methods":[{"technique":"manifest-analysis","confidence":0.8,"value":"/app/test_requirements.txt"},{"technique":"manifest-analysis","confidence":0.8,"value":"/app/setup.py"}]}]}},{"group":"","name":"packaging","version":"24.2","purl":"pkg:pypi/packaging@24.2","type":"library","bom-ref":"pkg:pypi/packaging@24.2","properties":[{"name":"SrcFile","value":"/app/test_requirements.txt"},{"name":"SrcFile","value":"/app/setup.py"}],"evidence":{"identity":[{"field":"purl","confidence":0.8,"methods":[{"technique":"manifest-analysis","confidence":0.8,"value":"/app/test_requirements.txt"},{"technique":"manifest-analysis","confidence":0.8,"value":"/app/setup.py"}]}]}},{"group":"","name":"exceptiongroup","version":"1.2.2","purl":"pkg:pypi/exceptiongroup@1.2.2","type":"library","bom-ref":"pkg:pypi/exceptiongroup@1.2.2","properties":[{"name":"SrcFile","value":"/app/test_requirements.txt"},{"name":"SrcFile","value":"/app/setup.py"}],"evidence":{"identity":[{"field":"purl","confidence":0.8,"methods":[{"technique":"manifest-analysis","confidence":0.8,"value":"/app/test_requirements.txt"},{"technique":"manifest-analysis","confidence":0.8,"value":"/app/setup.py"}]}]}},{"group":"","name":"pluggy","version":"1.5.0","purl":"pkg:pypi/pluggy@1.5.0","type":"library","bom-ref":"pkg:pypi/pluggy@1.5.0","properties":[{"name":"SrcFile","value":"/app/test_requirements.txt"},{"name":"SrcFile","value":"/app/setup.py"}],"evidence":{"identity":[{"field":"purl","confidence":0.8,"methods":[{"technique":"manifest-analysis","confidence":0.8,"value":"/app/test_requirements.txt"},{"technique":"manifest-analysis","confidence":0.8,"value":"/app/setup.py"}]}]}},{"group":"","name":"iniconfig","version":"2.0.0","purl":"pkg:pypi/iniconfig@2.0.0","type":"library","bom-ref":"pkg:pypi/iniconfig@2.0.0","properties":[{"name":"SrcFile","value":"/app/test_requirements.txt"},{"name":"SrcFile","value":"/app/setup.py"}],"evidence":{"identity":[{"field":"purl","confidence":0.8,"methods":[{"technique":"manifest-analysis","confidence":0.8,"value":"/app/test_requirements.txt"},{"technique":"manifest-analysis","confidence":0.8,"value":"/app/setup.py"}]}]}},{"group":"","name":"funcy","version":"2.0","purl":"pkg:pypi/funcy@2.0","type":"library","bom-ref":"pkg:pypi/funcy@2.0","properties":[{"name":"SrcFile","value":"/app/setup.py"}],"evidence":{"identity":[{"field":"purl","confidence":0.5,"methods":[{"technique":"instrumentation","confidence":0.5,"value":"/tmp/cdxgen-venv-3oZ5Ee"}],"concludedValue":"/tmp/cdxgen-venv-3oZ5Ee"}]}}],"dependencies":[{"ref":"pkg:pypi/app@latest","dependsOn":["pkg:pypi/funcy@2.0","pkg:pypi/pytest@7.4.3","pkg:pypi/whatever@0.7"]},{"ref":"pkg:pypi/whatever@0.7","dependsOn":[]},{"ref":"pkg:pypi/tomli@2.2.1","dependsOn":[]},{"ref":"pkg:pypi/packaging@24.2","dependsOn":[]},{"ref":"pkg:pypi/exceptiongroup@1.2.2","dependsOn":[]},{"ref":"pkg:pypi/pluggy@1.5.0","dependsOn":[]},{"ref":"pkg:pypi/iniconfig@2.0.0","dependsOn":[]},{"ref":"pkg:pypi/pytest@7.4.3","dependsOn":["pkg:pypi/exceptiongroup@1.2.2","pkg:pypi/iniconfig@2.0.0","pkg:pypi/packaging@24.2","pkg:pypi/pluggy@1.5.0","pkg:pypi/tomli@2.2.1"]},{"ref":"pkg:pypi/funcy@2.0","dependsOn":[]}],"annotations":[]}